MANIFEST.in
README.txt
requirements.txt
setup.py
test_requirements.txt
version.txt
cloudshell/__init__.py
cloudshell/api/__init__.py
cloudshell/api/cloudshell_api.py
cloudshell/api/common_cloudshell_api.py
cloudshell/helpers/__init__.py
cloudshell/helpers/scripts/__init__.py
cloudshell/helpers/scripts/cloudshell_dev_helpers.py
cloudshell/helpers/scripts/cloudshell_scripts_helpers.py
cloudshell_automation_api.egg-info/PKG-INFO
cloudshell_automation_api.egg-info/SOURCES.txt
cloudshell_automation_api.egg-info/dependency_links.txt
cloudshell_automation_api.egg-info/requires.txt
cloudshell_automation_api.egg-info/top_level.txt