Metadata-Version: 1.0
Name: cloudshell-automation-api
Version: 2020.1.0.178672
Summary: QualiSystems CloudShell API package
Home-page: http://www.qualisystems.com/
Author: QualiSystems
Author-email: info@qualisystems.com
License: UNKNOWN
Platform: UNKNOWN
